{
  "session_id": "0def782bd8274185a58323e9b10225f9",
  "document_id": "e0d8f3174cb540a285709afe8c02afcf",
  "source": "simulated_camera",
  "model_output_type": "academic_state_model",
  "mode": "simulated_mode_b",
  "started_at": 1779104763.4397783,
  "scenario": "default_engagement_confusion_recovery",
  "thresholds": {
    "confusion": {
      "confidence": 0.65,
      "duration_sec": 8
    },
    "frustration": {
      "confidence": 0.6,
      "duration_sec": 6
    },
    "boredom": {
      "confidence": 0.6,
      "duration_sec": 12
    },
    "engagement": {
      "confidence": 0.75,
      "duration_sec": 0
    }
  }
}